{
	"common": {
		"siteName": "المكتبة الإسلامية",
		"home": "الرئيسية",
		"books": "الكتب",
		"categories": "الأقسام",
		"authors": "المؤلفون",
		"search": "بحث",
		"about": "من نحن",
		"login": "تسجيل الدخول",
		"logout": "تسجيل الخروج",
		"admin": "لوحة التحكم",
		"language": "اللغة",
		"loading": "جار التحميل…",
		"noResults": "لا توجد نتائج",
		"viewAll": "عرض الكل",
		"readMore": "اقرأ المزيد",
		"download": "تحميل",
		"readOnline": "اقرأ مباشرة",
		"backToHome": "العودة للرئيسية",
		"copyright": "ملكية عامة",
		"allRightsReserved": "جميع الحقوق محفوظة"
	},
	"home": {
		"heroTitle": "المكتبة الإسلامية الإلكترونية",
		"heroSubtitle": "اطلع على آلاف الكتب الإسلامية الأصيلة من علماء السلف والمعاصرين — بالعربية والإنجليزية والبنغالية والأوردو.",
		"featuredBooks": "كتب مميزة",
		"browseCategories": "تصفح الأقسام",
		"popularAuthors": "أشهر المؤلفين",
		"latestAdditions": "أحدث الإضافات",
		"startReading": "ابدأ القراءة"
	},
	"search": {
		"placeholder": "ابحث بالعنوان أو المؤلف أو الكلمة المفتاحية…",
		"filterByCategory": "تصفية حسب القسم",
		"filterByLanguage": "تصفية حسب اللغة",
		"filterByEra": "تصفية حسب العصر",
		"resultsFor": "نتائج البحث عن",
		"sortBy": "ترتيب حسب",
		"relevance": "الصلة",
		"mostViewed": "الأكثر مشاهدة",
		"newest": "الأحدث",
		"classical": "العصر الكلاسيكي",
		"medieval": "العصور الوسطى",
		"contemporary": "المعاصر"
	},
	"book": {
		"details": "تفاصيل الكتاب",
		"author": "المؤلف",
		"category": "القسم",
		"language": "اللغة",
		"pages": "الصفحات",
		"views": "المشاهدات",
		"downloads": "التحميلات",
		"description": "الوصف",
		"relatedBooks": "كتب ذات صلة",
		"bookmark": "إشارة مرجعية",
		"bookmarkAdded": "تمت إضافة الإشارة المرجعية",
		"fullScreen": "ملء الشاشة",
		"exitFullScreen": "الخروج من ملء الشاشة",
		"page": "صفحة",
		"of": "من",
		"previousPage": "الصفحة السابقة",
		"nextPage": "الصفحة التالية",
		"goToPage": "انتقل إلى الصفحة"
	},
	"admin": {
		"dashboard": "لوحة التحكم",
		"uploadBook": "رفع كتاب",
		"manageBooks": "إدارة الكتب",
		"manageAuthors": "إدارة المؤلفين",
		"manageCategories": "إدارة الأقسام",
		"statistics": "الإحصائيات",
		"totalBooks": "إجمالي الكتب",
		"totalDownloads": "إجمالي التحميلات",
		"totalViews": "إجمالي المشاهدات",
		"totalUsers": "إجمالي المستخدمين",
		"manageUsers": "إدارة المستخدمين",
		"addAuthor": "إضافة مؤلف",
		"editAuthor": "تعديل المؤلف",
		"deleteAuthor": "حذف المؤلف",
		"addCategory": "إضافة قسم",
		"editCategory": "تعديل القسم",
		"deleteCategory": "حذف القسم",
		"editBook": "تعديل الكتاب",
		"deleteBook": "حذف الكتاب",
		"changeRole": "تغيير الدور",
		"confirmDelete": "هل أنت متأكد؟ لا يمكن التراجع عن هذا الإجراء.",
		"saveChanges": "حفظ التغييرات",
		"cancel": "إلغاء",
		"create": "إنشاء",
		"noResults": "لا توجد نتائج"
	},
	"auth": {
		"signIn": "تسجيل الدخول",
		"signUp": "إنشاء حساب",
		"email": "البريد الإلكتروني",
		"password": "كلمة المرور",
		"forgotPassword": "نسيت كلمة المرور؟",
		"noAccount": "ليس لديك حساب؟",
		"hasAccount": "لديك حساب بالفعل؟"
	}
}
